setup.py
nk_first_py/__init__.py
nk_first_py/image.py
nk_first_py/raster.py
nk_first_py.egg-info/PKG-INFO
nk_first_py.egg-info/SOURCES.txt
nk_first_py.egg-info/dependency_links.txt
nk_first_py.egg-info/top_level.txt