Metadata-Version: 1.0
Name: nk-first-py
Version: 0.1
Summary: Meu primeiro gradiente
Home-page: UNKNOWN
Author: Manoel Neco Jr
Author-email: necoengenheiro@gmail.com
License: UNKNOWN
Platform: UNKNOWN
